DataSynthesis131/__init__.py
DataSynthesis131/common/__init__.py
DataSynthesis131/common/common.py
DataSynthesis131/metrics131/__init__.py
DataSynthesis131/metrics131/quality_evaluator.py
DataSynthesis131/synthesizer131/__init__.py
DataSynthesis131/synthesizer131/synthesizer.py
datasynthesis131-0.0.2.dist-info/METADATA
datasynthesis131-0.0.2.dist-info/WHEEL
datasynthesis131-0.0.2.dist-info/licenses/LICENSE
datasynthesis131-0.0.2.dist-info/RECORD
